{"config":{"output_file":null,"full_docs":false,"pub_only":false,"reachable_only":false,"distro_crate":false,"signatures":false,"borrow_data":false},"version":"0.19.0","compilation":{"directory":"/home/madu/Documents/Rust/rust-webassembly-book/rustycheckers","program":"/home/madu/.rustup/toolchains/stable-x86_64-unknown-linux-gnu/bin/rls","arguments":[],"output":"/home/madu/Documents/Rust/rust-webassembly-book/rustycheckers/target/rls/debug/deps/librustycheckers-170ce9869a6ef8a3.rmeta"},"prelude":{"crate_id":{"name":"rustycheckers","disambiguator":[9959294417923412398,8270563389289814553]},"crate_root":"src","external_crates":[{"file_name":"/home/madu/Documents/Rust/rust-webassembly-book/rustycheckers/src/lib.rs","num":1,"id":{"name":"std","disambiguator":[14029911340352309513,3694302842271320647]}},{"file_name":"/home/madu/Documents/Rust/rust-webassembly-book/rustycheckers/src/lib.rs","num":2,"id":{"name":"core","disambiguator":[5366521311420338507,5001693844293236078]}},{"file_name":"/home/madu/Documents/Rust/rust-webassembly-book/rustycheckers/src/lib.rs","num":3,"id":{"name":"compiler_builtins","disambiguator":[16078967021793905033,18044181950654841110]}},{"file_name":"/home/madu/Documents/Rust/rust-webassembly-book/rustycheckers/src/lib.rs","num":4,"id":{"name":"rustc_std_workspace_core","disambiguator":[3256375668792353550,7694578384779899277]}},{"file_name":"/home/madu/Documents/Rust/rust-webassembly-book/rustycheckers/src/lib.rs","num":5,"id":{"name":"alloc","disambiguator":[17967524032803306908,5163911630854790873]}},{"file_name":"/home/madu/Documents/Rust/rust-webassembly-book/rustycheckers/src/lib.rs","num":6,"id":{"name":"libc","disambiguator":[7486411228932131176,10611882423765912104]}},{"file_name":"/home/madu/Documents/Rust/rust-webassembly-book/rustycheckers/src/lib.rs","num":7,"id":{"name":"unwind","disambiguator":[8951493940525711481,6598059053846807751]}},{"file_name":"/home/madu/Documents/Rust/rust-webassembly-book/rustycheckers/src/lib.rs","num":8,"id":{"name":"cfg_if","disambiguator":[6080538021290120973,12135415365643254465]}},{"file_name":"/home/madu/Documents/Rust/rust-webassembly-book/rustycheckers/src/lib.rs","num":9,"id":{"name":"backtrace","disambiguator":[2404946192574906823,11198495443784404083]}},{"file_name":"/home/madu/Documents/Rust/rust-webassembly-book/rustycheckers/src/lib.rs","num":10,"id":{"name":"rustc_demangle","disambiguator":[8156052144428984436,15205012491124168822]}},{"file_name":"/home/madu/Documents/Rust/rust-webassembly-book/rustycheckers/src/lib.rs","num":11,"id":{"name":"backtrace_sys","disambiguator":[11527475684179663565,15577722846879460413]}},{"file_name":"/home/madu/Documents/Rust/rust-webassembly-book/rustycheckers/src/lib.rs","num":12,"id":{"name":"hashbrown","disambiguator":[4615572763888095747,7180296191060376175]}},{"file_name":"/home/madu/Documents/Rust/rust-webassembly-book/rustycheckers/src/lib.rs","num":13,"id":{"name":"rustc_std_workspace_alloc","disambiguator":[16051702409717455556,18428390842256153874]}},{"file_name":"/home/madu/Documents/Rust/rust-webassembly-book/rustycheckers/src/lib.rs","num":14,"id":{"name":"panic_unwind","disambiguator":[14083788917415871355,15092499333930635081]}}],"span":{"file_name":"src/lib.rs","byte_start":0,"byte_end":10,"line_start":1,"line_end":1,"column_start":1,"column_end":11}},"imports":[],"defs":[{"kind":"Mod","id":{"krate":0,"index":0},"span":{"file_name":"src/lib.rs","byte_start":0,"byte_end":10,"line_start":1,"line_end":1,"column_start":1,"column_end":11},"name":"","qualname":"::","value":"src/lib.rs","parent":null,"children":[{"krate":0,"index":10},{"krate":0,"index":11},{"krate":0,"index":12}],"decl_id":null,"docs":"","sig":null,"attributes":[]},{"kind":"Mod","id":{"krate":0,"index":12},"span":{"file_name":"src/board.rs","byte_start":0,"byte_end":0,"line_start":1,"line_end":1,"column_start":1,"column_end":1},"name":"board","qualname":"::board","value":"src/board.rs","parent":null,"children":[{"krate":0,"index":16},{"krate":0,"index":28},{"krate":0,"index":26},{"krate":0,"index":23},{"krate":0,"index":24},{"krate":0,"index":21},{"krate":0,"index":29},{"krate":0,"index":40},{"krate":0,"index":38},{"krate":0,"index":34},{"krate":0,"index":35},{"krate":0,"index":32},{"krate":0,"index":13}],"decl_id":null,"docs":"","sig":null,"attributes":[]},{"kind":"TupleVariant","id":{"krate":0,"index":17},"span":{"file_name":"src/board.rs","byte_start":78,"byte_end":83,"line_start":4,"line_end":4,"column_start":5,"column_end":10},"name":"White","qualname":"::board::PieceColor::White","value":"PieceColor::White","parent":{"krate":0,"index":16},"children":[],"decl_id":null,"docs":"","sig":null,"attributes":[]},{"kind":"TupleVariant","id":{"krate":0,"index":19},"span":{"file_name":"src/board.rs","byte_start":89,"byte_end":94,"line_start":5,"line_end":5,"column_start":5,"column_end":10},"name":"Black","qualname":"::board::PieceColor::Black","value":"PieceColor::Black","parent":{"krate":0,"index":16},"children":[],"decl_id":null,"docs":"","sig":null,"attributes":[]},{"kind":"Enum","id":{"krate":0,"index":16},"span":{"file_name":"src/board.rs","byte_start":62,"byte_end":72,"line_start":3,"line_end":3,"column_start":10,"column_end":20},"name":"PieceColor","qualname":"::board::PieceColor","value":"PieceColor::{White, Black}","parent":null,"children":[{"krate":0,"index":17},{"krate":0,"index":19}],"decl_id":null,"docs":"","sig":null,"attributes":[]},{"kind":"Struct","id":{"krate":0,"index":29},"span":{"file_name":"src/board.rs","byte_start":151,"byte_end":160,"line_start":9,"line_end":9,"column_start":12,"column_end":21},"name":"GamePiece","qualname":"::board::GamePiece","value":"GamePiece { color, crowned }","parent":null,"children":[{"krate":0,"index":30},{"krate":0,"index":31}],"decl_id":null,"docs":"","sig":null,"attributes":[]},{"kind":"Field","id":{"krate":0,"index":30},"span":{"file_name":"src/board.rs","byte_start":170,"byte_end":175,"line_start":10,"line_end":10,"column_start":9,"column_end":14},"name":"color","qualname":"::board::GamePiece::color","value":"board::PieceColor","parent":{"krate":0,"index":29},"children":[],"decl_id":null,"docs":"","sig":null,"attributes":[]},{"kind":"Field","id":{"krate":0,"index":31},"span":{"file_name":"src/board.rs","byte_start":197,"byte_end":204,"line_start":11,"line_end":11,"column_start":9,"column_end":16},"name":"crowned","qualname":"::board::GamePiece::crowned","value":"bool","parent":{"krate":0,"index":29},"children":[],"decl_id":null,"docs":"","sig":null,"attributes":[]},{"kind":"Local","id":{"krate":0,"index":4294967279},"span":{"file_name":"src/board.rs","byte_start":246,"byte_end":251,"line_start":15,"line_end":15,"column_start":16,"column_end":21},"name":"color","qualname":"<GamePiece>::new::color","value":"board::PieceColor","parent":null,"children":[],"decl_id":null,"docs":"","sig":null,"attributes":[]},{"kind":"Method","id":{"krate":0,"index":14},"span":{"file_name":"src/board.rs","byte_start":242,"byte_end":245,"line_start":15,"line_end":15,"column_start":12,"column_end":15},"name":"new","qualname":"<GamePiece>::new","value":"fn (color: PieceColor) -> GamePiece","parent":null,"children":[],"decl_id":null,"docs":"","sig":null,"attributes":[]},{"kind":"Local","id":{"krate":0,"index":4294967264},"span":{"file_name":"src/board.rs","byte_start":379,"byte_end":380,"line_start":22,"line_end":22,"column_start":20,"column_end":21},"name":"p","qualname":"<GamePiece>::crowned::p","value":"board::GamePiece","parent":null,"children":[],"decl_id":null,"docs":"","sig":null,"attributes":[]},{"kind":"Method","id":{"krate":0,"index":15},"span":{"file_name":"src/board.rs","byte_start":371,"byte_end":378,"line_start":22,"line_end":22,"column_start":12,"column_end":19},"name":"crowned","qualname":"<GamePiece>::crowned","value":"fn (p: GamePiece) -> GamePiece","parent":null,"children":[],"decl_id":null,"docs":"","sig":null,"attributes":[]}],"impls":[{"id":0,"kind":"Inherent","span":{"file_name":"src/board.rs","byte_start":220,"byte_end":229,"line_start":14,"line_end":14,"column_start":6,"column_end":15},"value":"","parent":null,"children":[{"krate":0,"index":14},{"krate":0,"index":15}],"docs":"","sig":null,"attributes":[]}],"refs":[{"kind":"Mod","span":{"file_name":"src/lib.rs","byte_start":4,"byte_end":9,"line_start":1,"line_end":1,"column_start":5,"column_end":10},"ref_id":{"krate":0,"index":12}},{"kind":"Type","span":{"file_name":"src/board.rs","byte_start":177,"byte_end":187,"line_start":10,"line_end":10,"column_start":16,"column_end":26},"ref_id":{"krate":0,"index":16}},{"kind":"Variable","span":{"file_name":"src/board.rs","byte_start":170,"byte_end":175,"line_start":10,"line_end":10,"column_start":9,"column_end":14},"ref_id":{"krate":0,"index":30}},{"kind":"Variable","span":{"file_name":"src/board.rs","byte_start":197,"byte_end":204,"line_start":11,"line_end":11,"column_start":9,"column_end":16},"ref_id":{"krate":0,"index":31}},{"kind":"Variable","span":{"file_name":"src/board.rs","byte_start":170,"byte_end":175,"line_start":10,"line_end":10,"column_start":9,"column_end":14},"ref_id":{"krate":0,"index":30}},{"kind":"Variable","span":{"file_name":"src/board.rs","byte_start":197,"byte_end":204,"line_start":11,"line_end":11,"column_start":9,"column_end":16},"ref_id":{"krate":0,"index":31}},{"kind":"Variable","span":{"file_name":"src/board.rs","byte_start":170,"byte_end":175,"line_start":10,"line_end":10,"column_start":9,"column_end":14},"ref_id":{"krate":0,"index":30}},{"kind":"Variable","span":{"file_name":"src/board.rs","byte_start":197,"byte_end":204,"line_start":11,"line_end":11,"column_start":9,"column_end":16},"ref_id":{"krate":0,"index":31}},{"kind":"Variable","span":{"file_name":"src/board.rs","byte_start":170,"byte_end":175,"line_start":10,"line_end":10,"column_start":9,"column_end":14},"ref_id":{"krate":0,"index":30}},{"kind":"Variable","span":{"file_name":"src/board.rs","byte_start":197,"byte_end":204,"line_start":11,"line_end":11,"column_start":9,"column_end":16},"ref_id":{"krate":0,"index":31}},{"kind":"Variable","span":{"file_name":"src/board.rs","byte_start":170,"byte_end":175,"line_start":10,"line_end":10,"column_start":9,"column_end":14},"ref_id":{"krate":0,"index":30}},{"kind":"Variable","span":{"file_name":"src/board.rs","byte_start":197,"byte_end":204,"line_start":11,"line_end":11,"column_start":9,"column_end":16},"ref_id":{"krate":0,"index":31}},{"kind":"Type","span":{"file_name":"src/board.rs","byte_start":220,"byte_end":229,"line_start":14,"line_end":14,"column_start":6,"column_end":15},"ref_id":{"krate":0,"index":29}},{"kind":"Type","span":{"file_name":"src/board.rs","byte_start":252,"byte_end":262,"line_start":15,"line_end":15,"column_start":22,"column_end":32},"ref_id":{"krate":0,"index":16}},{"kind":"Type","span":{"file_name":"src/board.rs","byte_start":267,"byte_end":276,"line_start":15,"line_end":15,"column_start":37,"column_end":46},"ref_id":{"krate":0,"index":29}},{"kind":"Type","span":{"file_name":"src/board.rs","byte_start":286,"byte_end":295,"line_start":16,"line_end":16,"column_start":9,"column_end":18},"ref_id":{"krate":0,"index":29}},{"kind":"Variable","span":{"file_name":"src/board.rs","byte_start":309,"byte_end":314,"line_start":17,"line_end":17,"column_start":13,"column_end":18},"ref_id":{"krate":0,"index":30}},{"kind":"Variable","span":{"file_name":"src/board.rs","byte_start":309,"byte_end":314,"line_start":17,"line_end":17,"column_start":13,"column_end":18},"ref_id":{"krate":0,"index":4294967279}},{"kind":"Variable","span":{"file_name":"src/board.rs","byte_start":328,"byte_end":335,"line_start":18,"line_end":18,"column_start":13,"column_end":20},"ref_id":{"krate":0,"index":31}},{"kind":"Type","span":{"file_name":"src/board.rs","byte_start":382,"byte_end":391,"line_start":22,"line_end":22,"column_start":23,"column_end":32},"ref_id":{"krate":0,"index":29}},{"kind":"Type","span":{"file_name":"src/board.rs","byte_start":396,"byte_end":405,"line_start":22,"line_end":22,"column_start":37,"column_end":46},"ref_id":{"krate":0,"index":29}},{"kind":"Type","span":{"file_name":"src/board.rs","byte_start":415,"byte_end":424,"line_start":23,"line_end":23,"column_start":9,"column_end":18},"ref_id":{"krate":0,"index":29}},{"kind":"Variable","span":{"file_name":"src/board.rs","byte_start":438,"byte_end":443,"line_start":24,"line_end":24,"column_start":13,"column_end":18},"ref_id":{"krate":0,"index":30}},{"kind":"Variable","span":{"file_name":"src/board.rs","byte_start":444,"byte_end":445,"line_start":24,"line_end":24,"column_start":19,"column_end":20},"ref_id":{"krate":0,"index":4294967264}},{"kind":"Variable","span":{"file_name":"src/board.rs","byte_start":446,"byte_end":451,"line_start":24,"line_end":24,"column_start":21,"column_end":26},"ref_id":{"krate":0,"index":30}},{"kind":"Variable","span":{"file_name":"src/board.rs","byte_start":465,"byte_end":472,"line_start":25,"line_end":25,"column_start":13,"column_end":20},"ref_id":{"krate":0,"index":31}}],"macro_refs":[],"relations":[{"span":{"file_name":"src/board.rs","byte_start":220,"byte_end":229,"line_start":14,"line_end":14,"column_start":6,"column_end":15},"kind":{"Impl":{"id":0}},"from":{"krate":0,"index":29},"to":{"krate":4294967295,"index":4294967295}}]}